csp_bot/__init__.py
csp_bot/bot.py
csp_bot/bot_config.py
csp_bot/cli.py
csp_bot/structs.py
csp_bot/utils.py
csp_bot/backends/__init__.py
csp_bot/backends/discord.py
csp_bot/backends/slack.py
csp_bot/backends/symphony.py
csp_bot/commands/__init__.py
csp_bot/commands/base.py
csp_bot/commands/echo.py
csp_bot/commands/help.py
csp_bot/commands/schedule.py
csp_bot/commands/status.py
csp_bot/config/__init__.py
csp_bot/config/commands.yaml
csp_bot/config/conf.yaml
csp_bot/config/modules.yaml
csp_bot/config/gateway/all.yaml
csp_bot/config/gateway/discord.yaml
csp_bot/config/gateway/mixed.yaml
csp_bot/config/gateway/slack.yaml
csp_bot/config/gateway/symphony.yaml
csp_bot/config/hydra/job_logging/custom.yaml
csp_bot/gateway/__init__.py
csp_bot/gateway/gateway.py
csp_bot/tests/__init__.py
csp_bot/tests/conftest.py
csp_bot/tests/test_all.py
csp_bot/tests/test_bot.py
csp_bot/tests/test_config.py
csp_bot/tests/test_slack_entity_regex.py
csp_bot-1.1.0.dist-info/METADATA
csp_bot-1.1.0.dist-info/WHEEL
csp_bot-1.1.0.dist-info/entry_points.txt
csp_bot-1.1.0.dist-info/licenses/LICENSE
csp_bot-1.1.0.dist-info/RECORD
