Metadata-Version: 2.4
Name: csp-bot
Version: 1.1.0
Summary: CSP Bot
Project-URL: Repository, https://github.com/point72/csp-bot
Project-URL: Homepage, https://github.com/point72/csp-bot
Author-email: the csp-bot authors <CSPOpenSource@point72.com>
License: Apache-2.0
License-File: LICENSE
Keywords: chat,chatbot,csp,slack,stream-processing
Classifier: Development Status :: 3 - Alpha
Classifier: License :: OSI Approved :: Apache Software License
Classifier: Programming Language :: Python
Classifier: Programming Language :: Python :: 3
Classifier: Programming Language :: Python :: 3.9
Classifier: Programming Language :: Python :: 3.10
Classifier: Programming Language :: Python :: 3.11
Classifier: Programming Language :: Python :: 3.12
Classifier: Programming Language :: Python :: 3.13
Classifier: Programming Language :: Python :: Implementation :: CPython
Classifier: Programming Language :: Python :: Implementation :: PyPy
Requires-Python: >=3.9
Requires-Dist: beautifulsoup4
Requires-Dist: ccflow>=0.5.2
Requires-Dist: croniter
Requires-Dist: csp-gateway<3,>=2
Requires-Dist: csp<1,>=0.9
Requires-Dist: dateparser
Requires-Dist: hydra-core
Requires-Dist: pandas
Requires-Dist: pydantic>=2
Provides-Extra: develop
Requires-Dist: build; extra == 'develop'
Requires-Dist: bump-my-version; extra == 'develop'
Requires-Dist: check-manifest; extra == 'develop'
Requires-Dist: codespell<2.5,>=2.2.6; extra == 'develop'
Requires-Dist: csp-adapter-discord<0.2,>=0.1; extra == 'develop'
Requires-Dist: csp-adapter-slack<0.4,>=0.3; extra == 'develop'
Requires-Dist: csp-adapter-symphony<0.4,>=0.3; extra == 'develop'
Requires-Dist: hatchling; extra == 'develop'
Requires-Dist: mdformat-tables<1.1,>=1; extra == 'develop'
Requires-Dist: mdformat<0.8,>=0.7.17; extra == 'develop'
Requires-Dist: pytest; extra == 'develop'
Requires-Dist: pytest-cov; extra == 'develop'
Requires-Dist: ruff<0.10,>=0.5; extra == 'develop'
Requires-Dist: twine<7,>=5; extra == 'develop'
Requires-Dist: wheel; extra == 'develop'
